README.rst
setup.py
PyVMU.egg-info/PKG-INFO
PyVMU.egg-info/SOURCES.txt
PyVMU.egg-info/dependency_links.txt
PyVMU.egg-info/requires.txt
PyVMU.egg-info/top_level.txt
pyvmu/__init__.py
pyvmu/messages.py
pyvmu/vmu931.py